[
  {
    "file_source_team": "TeamA",
	"file_target_team": "AdminToolKit_D14_Dormant_Users_C_deactivate",
	"file_users_action": "remove",
	"file_roles_action": "keep"
  },
  {
    "file_source_team": "TeamB",
	"file_target_team": "AdminToolKit_D14_Dormant_Users_C_deactivate",
	"file_users_action": "remove",
	"file_roles_action": "keep"
  },
  {
    "file_source_team": "TeamA",
	"file_target_team": "AdminToolKit_D14_Dormant_Users_C_delete",
	"file_users_action": "remove",
	"file_roles_action": "keep"
  },
  {
    "file_source_team": "TeamB",
	"file_target_team": "AdminToolKit_D14_Dormant_Users_C_delete",
	"file_users_action": "remove",
	"file_roles_action": "keep"
  }
]